objconf/__init__.py
objconf/attributes.py
objconf/config.py
objconf-0.3.0.dist-info/LICENSE
objconf-0.3.0.dist-info/METADATA
objconf-0.3.0.dist-info/WHEEL
objconf-0.3.0.dist-info/top_level.txt
objconf-0.3.0.dist-info/RECORD
