Metadata-Version: 2.1
Name: objconf
Version: 0.3.0
Summary: Object configuration for Python projects
Home-page: https://github.com/milosta/objconf
Author: Miloslav Stanek
Author-email: milostanek@gmail.com
License: UNKNOWN
Platform: UNKNOWN
Requires-Python: >=3.6
Requires-Dist: pyaml
Provides-Extra: tests
Requires-Dist: pytest ; extra == 'tests'
Requires-Dist: flake8 ; extra == 'tests'
